flask_crossdomain_session/__init__.py
flask_crossdomain_session/injection.html
flask_crossdomain_session/model.py
flask_crossdomain_session/session_interface.py
flask_crossdomain_session/version.py
Flask_CrossDomain_Session-0.0.1.dist-info/LICENSE
Flask_CrossDomain_Session-0.0.1.dist-info/METADATA
Flask_CrossDomain_Session-0.0.1.dist-info/WHEEL
Flask_CrossDomain_Session-0.0.1.dist-info/top_level.txt
Flask_CrossDomain_Session-0.0.1.dist-info/zip-safe
Flask_CrossDomain_Session-0.0.1.dist-info/RECORD
